[
  {
    "id": "가려움_고유명사-1",
    "reason": "고유명사 (인명/지명)"
  },
  {
    "id": "가야_고유명사-1",
    "reason": "고유명사 (인명/지명)"
  },
  {
    "id": "가지_의존명사-1",
    "reason": "기능적 요소 (대명사/의존명사)"
  },
  {
    "id": "간_의존명사-1",
    "reason": "기능적 요소 (대명사/의존명사)"
  },
  {
    "id": "강남_고유명사-1",
    "reason": "고유명사 (인명/지명)"
  },
  {
    "id": "강북_고유명사-1",
    "reason": "고유명사 (인명/지명)"
  },
  {
    "id": "강북구_고유명사-1",
    "reason": "고유명사 (인명/지명)"
  },
  {
    "id": "개국_의존명사-1",
    "reason": "기능적 요소 (대명사/의존명사)"
  },
  {
    "id": "개월_의존명사-1",
    "reason": "기능적 요소 (대명사/의존명사)"
  },
  {
    "id": "거_의존명사-1",
    "reason": "기능적 요소 (대명사/의존명사)"
  },
  {
    "id": "거기_대명사-1",
    "reason": "기능적 요소 (대명사/의존명사)"
  },
  {
    "id": "건_의존명사-1",
    "reason": "기능적 요소 (대명사/의존명사)"
  },
  {
    "id": "것_의존명사-1",
    "reason": "기능적 요소 (대명사/의존명사)"
  },
  {
    "id": "겨를_의존명사-1",
    "reason": "기능적 요소 (대명사/의존명사)"
  },
  {
    "id": "격_의존명사-1",
    "reason": "기능적 요소 (대명사/의존명사)"
  },
  {
    "id": "겸_의존명사-1",
    "reason": "기능적 요소 (대명사/의존명사)"
  },
  {
    "id": "경기도_고유명사-1",
    "reason": "고유명사 (인명/지명)"
  },
  {
    "id": "경복궁_고유명사-1",
    "reason": "고유명사 (인명/지명)"
  },
  {
    "id": "경주_고유명사-1",
    "reason": "고유명사 (인명/지명)"
  },
  {
    "id": "고종_고유명사-1",
    "reason": "고유명사 (인명/지명)"
  },
  {
    "id": "고흐_고유명사-1",
    "reason": "고유명사 (인명/지명)"
  },
  {
    "id": "공공장소_고유명사-1",
    "reason": "고유명사 (인명/지명)"
  },
  {
    "id": "광주_고유명사-1",
    "reason": "고유명사 (인명/지명)"
  },
  {
    "id": "광화문_고유명사-1",
    "reason": "고유명사 (인명/지명)"
  },
  {
    "id": "광화문역_고유명사-1",
    "reason": "고유명사 (인명/지명)"
  },
  {
    "id": "교열_고유명사-1",
    "reason": "고유명사 (인명/지명)"
  },
  {
    "id": "구리시_고유명사-1",
    "reason": "고유명사 (인명/지명)"
  },
  {
    "id": "구미_고유명사-1",
    "reason": "고유명사 (인명/지명)"
  },
  {
    "id": "구민_고유명사-1",
    "reason": "고유명사 (인명/지명)"
  },
  {
    "id": "국가대표_고유명사-1",
    "reason": "고유명사 (인명/지명)"
  },
  {
    "id": "국립발레단_고유명사-1",
    "reason": "고유명사 (인명/지명)"
  },
  {
    "id": "군_의존명사-1",
    "reason": "기능적 요소 (대명사/의존명사)"
  },
  {
    "id": "군데_의존명사-1",
    "reason": "기능적 요소 (대명사/의존명사)"
  },
  {
    "id": "그_대명사-1",
    "reason": "기능적 요소 (대명사/의존명사)"
  },
  {
    "id": "그거_대명사-1",
    "reason": "기능적 요소 (대명사/의존명사)"
  },
  {
    "id": "그것_대명사-1",
    "reason": "기능적 요소 (대명사/의존명사)"
  },
  {
    "id": "그곳_대명사-1",
    "reason": "기능적 요소 (대명사/의존명사)"
  },
  {
    "id": "그녀_대명사-1",
    "reason": "기능적 요소 (대명사/의존명사)"
  },
  {
    "id": "그분_대명사-1",
    "reason": "기능적 요소 (대명사/의존명사)"
  },
  {
    "id": "극동_고유명사-1",
    "reason": "고유명사 (인명/지명)"
  },
  {
    "id": "금강산_고유명사-1",
    "reason": "고유명사 (인명/지명)"
  },
  {
    "id": "금반지_고유명사-1",
    "reason": "고유명사 (인명/지명)"
  },
  {
    "id": "금산_고유명사-1",
    "reason": "고유명사 (인명/지명)"
  },
  {
    "id": "김경_고유명사-1",
    "reason": "고유명사 (인명/지명)"
  },
  {
    "id": "김동진_고유명사-1",
    "reason": "고유명사 (인명/지명)"
  },
  {
    "id": "김미경_고유명사-1",
    "reason": "고유명사 (인명/지명)"
  },
  {
    "id": "김민_고유명사-1",
    "reason": "고유명사 (인명/지명)"
  },
  {
    "id": "김민기_고유명사-1",
    "reason": "고유명사 (인명/지명)"
  },
  {
    "id": "김민석_고유명사-1",
    "reason": "고유명사 (인명/지명)"
  },
  {
    "id": "김민수_고유명사-1",
    "reason": "고유명사 (인명/지명)"
  },
  {
    "id": "김민우_고유명사-1",
    "reason": "고유명사 (인명/지명)"
  },
  {
    "id": "김소연_고유명사-1",
    "reason": "고유명사 (인명/지명)"
  },
  {
    "id": "김수미_고유명사-1",
    "reason": "고유명사 (인명/지명)"
  },
  {
    "id": "김수정_고유명사-1",
    "reason": "고유명사 (인명/지명)"
  },
  {
    "id": "김수진_고유명사-1",
    "reason": "고유명사 (인명/지명)"
  },
  {
    "id": "김영_고유명사-1",
    "reason": "고유명사 (인명/지명)"
  },
  {
    "id": "김영수_고유명사-1",
    "reason": "고유명사 (인명/지명)"
  },
  {
    "id": "김영재_고유명사-1",
    "reason": "고유명사 (인명/지명)"
  },
  {
    "id": "김유미_고유명사-1",
    "reason": "고유명사 (인명/지명)"
  },
  {
    "id": "김윤미_고유명사-1",
    "reason": "고유명사 (인명/지명)"
  },
  {
    "id": "김제_고유명사-1",
    "reason": "고유명사 (인명/지명)"
  },
  {
    "id": "김준_고유명사-1",
    "reason": "고유명사 (인명/지명)"
  },
  {
    "id": "김준호_고유명사-1",
    "reason": "고유명사 (인명/지명)"
  },
  {
    "id": "김지호_고유명사-1",
    "reason": "고유명사 (인명/지명)"
  },
  {
    "id": "김철수_고유명사-1",
    "reason": "고유명사 (인명/지명)"
  },
  {
    "id": "김현수_고유명사-1",
    "reason": "고유명사 (인명/지명)"
  },
  {
    "id": "끌개_고유명사-1",
    "reason": "고유명사 (인명/지명)"
  },
  {
    "id": "나름_의존명사-1",
    "reason": "기능적 요소 (대명사/의존명사)"
  },
  {
    "id": "나이팅게일_고유명사-1",
    "reason": "고유명사 (인명/지명)"
  },
  {
    "id": "낙동강_고유명사-1",
    "reason": "고유명사 (인명/지명)"
  },
  {
    "id": "남극_고유명사-1",
    "reason": "고유명사 (인명/지명)"
  },
  {
    "id": "남대문_고유명사-1",
    "reason": "고유명사 (인명/지명)"
  },
  {
    "id": "남대문시장_고유명사-1",
    "reason": "고유명사 (인명/지명)"
  },
  {
    "id": "남산_고유명사-1",
    "reason": "고유명사 (인명/지명)"
  },
  {
    "id": "남이섬_고유명사-1",
    "reason": "고유명사 (인명/지명)"
  },
  {
    "id": "남한_고유명사-1",
    "reason": "고유명사 (인명/지명)"
  },
  {
    "id": "남해_고유명사-1",
    "reason": "고유명사 (인명/지명)"
  },
  {
    "id": "남해안_고유명사-1",
    "reason": "고유명사 (인명/지명)"
  },
  {
    "id": "내_의존명사-1",
    "reason": "기능적 요소 (대명사/의존명사)"
  },
  {
    "id": "년_의존명사-1",
    "reason": "기능적 요소 (대명사/의존명사)"
  },
  {
    "id": "년대_의존명사-1",
    "reason": "기능적 요소 (대명사/의존명사)"
  },
  {
    "id": "년도_의존명사-1",
    "reason": "기능적 요소 (대명사/의존명사)"
  },
  {
    "id": "노고단_고유명사-1",
    "reason": "고유명사 (인명/지명)"
  },
  {
    "id": "놀부_고유명사-1",
    "reason": "고유명사 (인명/지명)"
  },
  {
    "id": "놀이공원_고유명사-1",
    "reason": "고유명사 (인명/지명)"
  },
  {
    "id": "놈_의존명사-1",
    "reason": "기능적 요소 (대명사/의존명사)"
  },
  {
    "id": "농심_고유명사-1",
    "reason": "고유명사 (인명/지명)"
  },
  {
    "id": "누구_대명사-1",
    "reason": "기능적 요소 (대명사/의존명사)"
  },
  {
    "id": "뉴욕_고유명사-1",
    "reason": "고유명사 (인명/지명)"
  },
  {
    "id": "달무지개_고유명사-1",
    "reason": "고유명사 (인명/지명)"
  },
  {
    "id": "당신_대명사-1",
    "reason": "기능적 요소 (대명사/의존명사)"
  },
  {
    "id": "대_의존명사-1",
    "reason": "기능적 요소 (대명사/의존명사)"
  },
  {
    "id": "대구_고유명사-1",
    "reason": "고유명사 (인명/지명)"
  },
  {
    "id": "대구광역시_고유명사-1",
    "reason": "고유명사 (인명/지명)"
  },
  {
    "id": "대로_의존명사-1",
    "reason": "기능적 요소 (대명사/의존명사)"
  },
  {
    "id": "대서양_고유명사-1",
    "reason": "고유명사 (인명/지명)"
  },
  {
    "id": "대전_고유명사-1",
    "reason": "고유명사 (인명/지명)"
  },
  {
    "id": "대학로_고유명사-1",
    "reason": "고유명사 (인명/지명)"
  },
  {
    "id": "대한_고유명사-1",
    "reason": "고유명사 (인명/지명)"
  },
  {
    "id": "대한민국_고유명사-1",
    "reason": "고유명사 (인명/지명)"
  },
  {
    "id": "데_의존명사-1",
    "reason": "기능적 요소 (대명사/의존명사)"
  },
  {
    "id": "도르래_고유명사-1",
    "reason": "고유명사 (인명/지명)"
  },
  {
    "id": "도시철도공사_고유명사-1",
    "reason": "고유명사 (인명/지명)"
  },
  {
    "id": "독일_고유명사-1",
    "reason": "고유명사 (인명/지명)"
  },
  {
    "id": "동경이_고유명사-1",
    "reason": "고유명사 (인명/지명)"
  },
  {
    "id": "동궐도_고유명사-1",
    "reason": "고유명사 (인명/지명)"
  },
  {
    "id": "동남아_고유명사-1",
    "reason": "고유명사 (인명/지명)"
  },
  {
    "id": "동남아시아_고유명사-1",
    "reason": "고유명사 (인명/지명)"
  },
  {
    "id": "동대문_고유명사-1",
    "reason": "고유명사 (인명/지명)"
  },
  {
    "id": "동문시장_고유명사-1",
    "reason": "고유명사 (인명/지명)"
  },
  {
    "id": "동해_고유명사-1",
    "reason": "고유명사 (인명/지명)"
  },
  {
    "id": "돼지풀_고유명사-1",
    "reason": "고유명사 (인명/지명)"
  },
  {
    "id": "두물머리_고유명사-1",
    "reason": "고유명사 (인명/지명)"
  },
  {
    "id": "둥_의존명사-1",
    "reason": "기능적 요소 (대명사/의존명사)"
  },
  {
    "id": "듯_의존명사-1",
    "reason": "기능적 요소 (대명사/의존명사)"
  },
  {
    "id": "듯이_의존명사-1",
    "reason": "기능적 요소 (대명사/의존명사)"
  },
  {
    "id": "등_의존명사-1",
    "reason": "기능적 요소 (대명사/의존명사)"
  },
  {
    "id": "디마케팅_고유명사-1",
    "reason": "고유명사 (인명/지명)"
  },
  {
    "id": "따름_의존명사-1",
    "reason": "기능적 요소 (대명사/의존명사)"
  },
  {
    "id": "땅끝마을_고유명사-1",
    "reason": "고유명사 (인명/지명)"
  },
  {
    "id": "때문_의존명사-1",
    "reason": "기능적 요소 (대명사/의존명사)"
  },
  {
    "id": "로마_고유명사-1",
    "reason": "고유명사 (인명/지명)"
  },
  {
    "id": "리스본_고유명사-1",
    "reason": "고유명사 (인명/지명)"
  },
  {
    "id": "마리_의존명사-1",
    "reason": "기능적 요소 (대명사/의존명사)"
  },
  {
    "id": "마이클_고유명사-1",
    "reason": "고유명사 (인명/지명)"
  },
  {
    "id": "마키아벨리_고유명사-1",
    "reason": "고유명사 (인명/지명)"
  },
  {
    "id": "만치_의존명사-1",
    "reason": "기능적 요소 (대명사/의존명사)"
  },
  {
    "id": "만큼_의존명사-1",
    "reason": "기능적 요소 (대명사/의존명사)"
  },
  {
    "id": "망정_의존명사-1",
    "reason": "기능적 요소 (대명사/의존명사)"
  },
  {
    "id": "매_의존명사-1",
    "reason": "기능적 요소 (대명사/의존명사)"
  },
  {
    "id": "맹금류_고유명사-1",
    "reason": "고유명사 (인명/지명)"
  },
  {
    "id": "메가_의존명사-1",
    "reason": "기능적 요소 (대명사/의존명사)"
  },
  {
    "id": "메디치_고유명사-1",
    "reason": "고유명사 (인명/지명)"
  },
  {
    "id": "메타_고유명사-1",
    "reason": "고유명사 (인명/지명)"
  },
  {
    "id": "면제배갑_고유명사-1",
    "reason": "고유명사 (인명/지명)"
  },
  {
    "id": "명_의존명사-1",
    "reason": "기능적 요소 (대명사/의존명사)"
  },
  {
    "id": "명동_고유명사-1",
    "reason": "고유명사 (인명/지명)"
  },
  {
    "id": "모나리자_고유명사-1",
    "reason": "고유명사 (인명/지명)"
  },
  {
    "id": "모래시계_고유명사-1",
    "reason": "고유명사 (인명/지명)"
  },
  {
    "id": "모시풀_고유명사-1",
    "reason": "고유명사 (인명/지명)"
  },
  {
    "id": "모자_고유명사-1",
    "reason": "고유명사 (인명/지명)"
  },
  {
    "id": "몰리_고유명사-1",
    "reason": "고유명사 (인명/지명)"
  },
  {
    "id": "무렵_의존명사-1",
    "reason": "기능적 요소 (대명사/의존명사)"
  },
  {
    "id": "무어_대명사-1",
    "reason": "기능적 요소 (대명사/의존명사)"
  },
  {
    "id": "무엇_대명사-1",
    "reason": "기능적 요소 (대명사/의존명사)"
  },
  {
    "id": "무정_고유명사-1",
    "reason": "고유명사 (인명/지명)"
  },
  {
    "id": "뭐_대명사-1",
    "reason": "기능적 요소 (대명사/의존명사)"
  },
  {
    "id": "미국_고유명사-1",
    "reason": "고유명사 (인명/지명)"
  },
  {
    "id": "미미_고유명사-1",
    "reason": "고유명사 (인명/지명)"
  },
  {
    "id": "미연_고유명사-1",
    "reason": "고유명사 (인명/지명)"
  },
  {
    "id": "미연이_고유명사-1",
    "reason": "고유명사 (인명/지명)"
  },
  {
    "id": "미영_고유명사-1",
    "reason": "고유명사 (인명/지명)"
  },
  {
    "id": "미터_의존명사-1",
    "reason": "기능적 요소 (대명사/의존명사)"
  },
  {
    "id": "민수_고유명사-1",
    "reason": "고유명사 (인명/지명)"
  },
  {
    "id": "민우_고유명사-1",
    "reason": "고유명사 (인명/지명)"
  },
  {
    "id": "민욱_고유명사-1",
    "reason": "고유명사 (인명/지명)"
  },
  {
    "id": "민호_고유명사-1",
    "reason": "고유명사 (인명/지명)"
  },
  {
    "id": "민희_고유명사-1",
    "reason": "고유명사 (인명/지명)"
  },
  {
    "id": "바_의존명사-1",
    "reason": "기능적 요소 (대명사/의존명사)"
  },
  {
    "id": "바질_고유명사-1",
    "reason": "고유명사 (인명/지명)"
  },
  {
    "id": "박선호_고유명사-1",
    "reason": "고유명사 (인명/지명)"
  },
  {
    "id": "박인수_고유명사-1",
    "reason": "고유명사 (인명/지명)"
  },
  {
    "id": "박정은_고유명사-1",
    "reason": "고유명사 (인명/지명)"
  },
  {
    "id": "박주연_고유명사-1",
    "reason": "고유명사 (인명/지명)"
  },
  {
    "id": "박지은_고유명사-1",
    "reason": "고유명사 (인명/지명)"
  },
  {
    "id": "박지훈_고유명사-1",
    "reason": "고유명사 (인명/지명)"
  },
  {
    "id": "박철수_고유명사-1",
    "reason": "고유명사 (인명/지명)"
  },
  {
    "id": "방음벽_고유명사-1",
    "reason": "고유명사 (인명/지명)"
  },
  {
    "id": "배추흰나비_고유명사-1",
    "reason": "고유명사 (인명/지명)"
  },
  {
    "id": "백제_고유명사-1",
    "reason": "고유명사 (인명/지명)"
  },
  {
    "id": "백조_고유명사-1",
    "reason": "고유명사 (인명/지명)"
  },
  {
    "id": "번_의존명사-1",
    "reason": "기능적 요소 (대명사/의존명사)"
  },
  {
    "id": "법_의존명사-1",
    "reason": "기능적 요소 (대명사/의존명사)"
  },
  {
    "id": "베트남_고유명사-1",
    "reason": "고유명사 (인명/지명)"
  },
  {
    "id": "병석_고유명사-1",
    "reason": "고유명사 (인명/지명)"
  },
  {
    "id": "보정_고유명사-1",
    "reason": "고유명사 (인명/지명)"
  },
  {
    "id": "부_의존명사-1",
    "reason": "기능적 요소 (대명사/의존명사)"
  },
  {
    "id": "부산시_고유명사-1",
    "reason": "고유명사 (인명/지명)"
  },
  {
    "id": "부천_고유명사-1",
    "reason": "고유명사 (인명/지명)"
  },
  {
    "id": "북_고유명사-1",
    "reason": "고유명사 (인명/지명)"
  },
  {
    "id": "북유럽_고유명사-1",
    "reason": "고유명사 (인명/지명)"
  },
  {
    "id": "북촌_고유명사-1",
    "reason": "고유명사 (인명/지명)"
  },
  {
    "id": "북한_고유명사-1",
    "reason": "고유명사 (인명/지명)"
  },
  {
    "id": "분_의존명사-1",
    "reason": "기능적 요소 (대명사/의존명사)"
  },
  {
    "id": "불국사_고유명사-1",
    "reason": "고유명사 (인명/지명)"
  },
  {
    "id": "브라질_고유명사-1",
    "reason": "고유명사 (인명/지명)"
  },
  {
    "id": "빅토르_고유명사-1",
    "reason": "고유명사 (인명/지명)"
  },
  {
    "id": "뻔_의존명사-1",
    "reason": "기능적 요소 (대명사/의존명사)"
  },
  {
    "id": "뿐_의존명사-1",
    "reason": "기능적 요소 (대명사/의존명사)"
  },
  {
    "id": "사직로_고유명사-1",
    "reason": "고유명사 (인명/지명)"
  },
  {
    "id": "삼일_고유명사-1",
    "reason": "고유명사 (인명/지명)"
  },
  {
    "id": "삼청동_고유명사-1",
    "reason": "고유명사 (인명/지명)"
  },
  {
    "id": "상철_고유명사-1",
    "reason": "고유명사 (인명/지명)"
  },
  {
    "id": "상훈_고유명사-1",
    "reason": "고유명사 (인명/지명)"
  },
  {
    "id": "샤오밍_고유명사-1",
    "reason": "고유명사 (인명/지명)"
  },
  {
    "id": "섀시_고유명사-1",
    "reason": "고유명사 (인명/지명)"
  },
  {
    "id": "서울시_고유명사-1",
    "reason": "고유명사 (인명/지명)"
  },
  {
    "id": "서울시청_고유명사-1",
    "reason": "고유명사 (인명/지명)"
  },
  {
    "id": "서울역_고유명사-1",
    "reason": "고유명사 (인명/지명)"
  },
  {
    "id": "서울역사박물관_고유명사-1",
    "reason": "고유명사 (인명/지명)"
  },
  {
    "id": "서유구_고유명사-1",
    "reason": "고유명사 (인명/지명)"
  },
  {
    "id": "석주명_고유명사-1",
    "reason": "고유명사 (인명/지명)"
  },
  {
    "id": "선비_고유명사-1",
    "reason": "고유명사 (인명/지명)"
  },
  {
    "id": "설악_고유명사-1",
    "reason": "고유명사 (인명/지명)"
  },
  {
    "id": "설악산_고유명사-1",
    "reason": "고유명사 (인명/지명)"
  },
  {
    "id": "성북_고유명사-1",
    "reason": "고유명사 (인명/지명)"
  },
  {
    "id": "성재_고유명사-1",
    "reason": "고유명사 (인명/지명)"
  },
  {
    "id": "성충_고유명사-1",
    "reason": "고유명사 (인명/지명)"
  },
  {
    "id": "세계평화공원_고유명사-1",
    "reason": "고유명사 (인명/지명)"
  },
  {
    "id": "세밀화_고유명사-1",
    "reason": "고유명사 (인명/지명)"
  },
  {
    "id": "세잔_고유명사-1",
    "reason": "고유명사 (인명/지명)"
  },
  {
    "id": "세종_고유명사-1",
    "reason": "고유명사 (인명/지명)"
  },
  {
    "id": "세종대왕_고유명사-1",
    "reason": "고유명사 (인명/지명)"
  },
  {
    "id": "세쿼이아_고유명사-1",
    "reason": "고유명사 (인명/지명)"
  },
  {
    "id": "센티미터_의존명사-1",
    "reason": "기능적 요소 (대명사/의존명사)"
  },
  {
    "id": "셈_의존명사-1",
    "reason": "기능적 요소 (대명사/의존명사)"
  },
  {
    "id": "소나_고유명사-1",
    "reason": "고유명사 (인명/지명)"
  },
  {
    "id": "소목_고유명사-1",
    "reason": "고유명사 (인명/지명)"
  },
  {
    "id": "소양강_고유명사-1",
    "reason": "고유명사 (인명/지명)"
  },
  {
    "id": "소정_고유명사-1",
    "reason": "고유명사 (인명/지명)"
  },
  {
    "id": "소행성_고유명사-1",
    "reason": "고유명사 (인명/지명)"
  },
  {
    "id": "소희_고유명사-1",
    "reason": "고유명사 (인명/지명)"
  },
  {
    "id": "송전_고유명사-1",
    "reason": "고유명사 (인명/지명)"
  },
  {
    "id": "송정_고유명사-1",
    "reason": "고유명사 (인명/지명)"
  },
  {
    "id": "수_의존명사-1",
    "reason": "기능적 요소 (대명사/의존명사)"
  },
  {
    "id": "수라_고유명사-1",
    "reason": "고유명사 (인명/지명)"
  },
  {
    "id": "수라상_고유명사-1",
    "reason": "고유명사 (인명/지명)"
  },
  {
    "id": "수로왕_고유명사-1",
    "reason": "고유명사 (인명/지명)"
  },
  {
    "id": "수미_고유명사-1",
    "reason": "고유명사 (인명/지명)"
  },
  {
    "id": "수민_고유명사-1",
    "reason": "고유명사 (인명/지명)"
  },
  {
    "id": "수연_고유명사-1",
    "reason": "고유명사 (인명/지명)"
  },
  {
    "id": "수원_고유명사-1",
    "reason": "고유명사 (인명/지명)"
  },
  {
    "id": "수잔_고유명사-1",
    "reason": "고유명사 (인명/지명)"
  },
  {
    "id": "수진_고유명사-1",
    "reason": "고유명사 (인명/지명)"
  },
  {
    "id": "수표교_고유명사-1",
    "reason": "고유명사 (인명/지명)"
  },
  {
    "id": "수희_고유명사-1",
    "reason": "고유명사 (인명/지명)"
  },
  {
    "id": "순_의존명사-1",
    "reason": "기능적 요소 (대명사/의존명사)"
  },
  {
    "id": "순천_고유명사-1",
    "reason": "고유명사 (인명/지명)"
  },
  {
    "id": "술_의존명사-1",
    "reason": "기능적 요소 (대명사/의존명사)"
  },
  {
    "id": "시리우스_고유명사-1",
    "reason": "고유명사 (인명/지명)"
  },
  {
    "id": "시청역_고유명사-1",
    "reason": "고유명사 (인명/지명)"
  },
  {
    "id": "식_의존명사-1",
    "reason": "기능적 요소 (대명사/의존명사)"
  },
  {
    "id": "신라_고유명사-1",
    "reason": "고유명사 (인명/지명)"
  },
  {
    "id": "실리콘밸리_고유명사-1",
    "reason": "고유명사 (인명/지명)"
  },
  {
    "id": "쓰개_고유명사-1",
    "reason": "고유명사 (인명/지명)"
  },
  {
    "id": "쓰개치마_고유명사-1",
    "reason": "고유명사 (인명/지명)"
  },
  {
    "id": "씨_의존명사-1",
    "reason": "기능적 요소 (대명사/의존명사)"
  },
  {
    "id": "아마존_고유명사-1",
    "reason": "고유명사 (인명/지명)"
  },
  {
    "id": "아무거_대명사-1",
    "reason": "기능적 요소 (대명사/의존명사)"
  },
  {
    "id": "아시아_고유명사-1",
    "reason": "고유명사 (인명/지명)"
  },
  {
    "id": "아시안_고유명사-1",
    "reason": "고유명사 (인명/지명)"
  },
  {
    "id": "아이돌_고유명사-1",
    "reason": "고유명사 (인명/지명)"
  },
  {
    "id": "아프리카_고유명사-1",
    "reason": "고유명사 (인명/지명)"
  },
  {
    "id": "안나_고유명사-1",
    "reason": "고유명사 (인명/지명)"
  },
  {
    "id": "안데르센_고유명사-1",
    "reason": "고유명사 (인명/지명)"
  },
  {
    "id": "알리_고유명사-1",
    "reason": "고유명사 (인명/지명)"
  },
  {
    "id": "애기장대_고유명사-1",
    "reason": "고유명사 (인명/지명)"
  },
  {
    "id": "약수역_고유명사-1",
    "reason": "고유명사 (인명/지명)"
  },
  {
    "id": "양산_고유명사-1",
    "reason": "고유명사 (인명/지명)"
  },
  {
    "id": "어디_대명사-1",
    "reason": "기능적 요소 (대명사/의존명사)"
  },
  {
    "id": "에디슨_고유명사-1",
    "reason": "고유명사 (인명/지명)"
  },
  {
    "id": "에르덴_고유명사-1",
    "reason": "고유명사 (인명/지명)"
  },
  {
    "id": "에티오피아_고유명사-1",
    "reason": "고유명사 (인명/지명)"
  },
  {
    "id": "엔도르핀_고유명사-1",
    "reason": "고유명사 (인명/지명)"
  },
  {
    "id": "여기_대명사-1",
    "reason": "기능적 요소 (대명사/의존명사)"
  },
  {
    "id": "여러분_대명사-1",
    "reason": "기능적 요소 (대명사/의존명사)"
  },
  {
    "id": "여수_고유명사-1",
    "reason": "고유명사 (인명/지명)"
  },
  {
    "id": "여의도_고유명사-1",
    "reason": "고유명사 (인명/지명)"
  },
  {
    "id": "여지_의존명사-1",
    "reason": "기능적 요소 (대명사/의존명사)"
  },
  {
    "id": "영국_고유명사-1",
    "reason": "고유명사 (인명/지명)"
  },
  {
    "id": "영수_고유명사-1",
    "reason": "고유명사 (인명/지명)"
  },
  {
    "id": "영어_고유명사-1",
    "reason": "고유명사 (인명/지명)"
  },
  {
    "id": "영우_고유명사-1",
    "reason": "고유명사 (인명/지명)"
  },
  {
    "id": "영월_고유명사-1",
    "reason": "고유명사 (인명/지명)"
  },
  {
    "id": "영진_고유명사-1",
    "reason": "고유명사 (인명/지명)"
  },
  {
    "id": "오기_고유명사-1",
    "reason": "고유명사 (인명/지명)"
  },
  {
    "id": "오딘_고유명사-1",
    "reason": "고유명사 (인명/지명)"
  },
  {
    "id": "오인혜_고유명사-1",
    "reason": "고유명사 (인명/지명)"
  },
  {
    "id": "오자와_고유명사-1",
    "reason": "고유명사 (인명/지명)"
  },
  {
    "id": "오토_고유명사-1",
    "reason": "고유명사 (인명/지명)"
  },
  {
    "id": "와_접속조사-1",
    "reason": "기능적 요소 (대명사/의존명사)"
  },
  {
    "id": "왕도_고유명사-1",
    "reason": "고유명사 (인명/지명)"
  },
  {
    "id": "왕업_고유명사-1",
    "reason": "고유명사 (인명/지명)"
  },
  {
    "id": "외_의존명사-1",
    "reason": "기능적 요소 (대명사/의존명사)"
  },
  {
    "id": "요것_대명사-1",
    "reason": "기능적 요소 (대명사/의존명사)"
  },
  {
    "id": "우리_대명사-1",
    "reason": "기능적 요소 (대명사/의존명사)"
  },
  {
    "id": "우방_고유명사-1",
    "reason": "고유명사 (인명/지명)"
  },
  {
    "id": "울산_고유명사-1",
    "reason": "고유명사 (인명/지명)"
  },
  {
    "id": "원_의존명사-1",
    "reason": "기능적 요소 (대명사/의존명사)"
  },
  {
    "id": "원뿔_고유명사-1",
    "reason": "고유명사 (인명/지명)"
  },
  {
    "id": "유라시아_고유명사-1",
    "reason": "고유명사 (인명/지명)"
  },
  {
    "id": "유럽_고유명사-1",
    "reason": "고유명사 (인명/지명)"
  },
  {
    "id": "유미_고유명사-1",
    "reason": "고유명사 (인명/지명)"
  },
  {
    "id": "유전체_고유명사-1",
    "reason": "고유명사 (인명/지명)"
  },
  {
    "id": "유칼립투스_고유명사-1",
    "reason": "고유명사 (인명/지명)"
  },
  {
    "id": "유코_고유명사-1",
    "reason": "고유명사 (인명/지명)"
  },
  {
    "id": "은수_고유명사-1",
    "reason": "고유명사 (인명/지명)"
  },
  {
    "id": "은영_고유명사-1",
    "reason": "고유명사 (인명/지명)"
  },
  {
    "id": "은정_고유명사-1",
    "reason": "고유명사 (인명/지명)"
  },
  {
    "id": "이거_대명사-1",
    "reason": "기능적 요소 (대명사/의존명사)"
  },
  {
    "id": "이건우_고유명사-1",
    "reason": "고유명사 (인명/지명)"
  },
  {
    "id": "이것_대명사-1",
    "reason": "기능적 요소 (대명사/의존명사)"
  },
  {
    "id": "이곳_대명사-1",
    "reason": "기능적 요소 (대명사/의존명사)"
  },
  {
    "id": "이나_접속조사-1",
    "reason": "기능적 요소 (대명사/의존명사)"
  },
  {
    "id": "이랑_접속조사-1",
    "reason": "기능적 요소 (대명사/의존명사)"
  },
  {
    "id": "이래_의존명사-1",
    "reason": "기능적 요소 (대명사/의존명사)"
  },
  {
    "id": "이며_접속조사-1",
    "reason": "기능적 요소 (대명사/의존명사)"
  },
  {
    "id": "이소영_고유명사-1",
    "reason": "고유명사 (인명/지명)"
  },
  {
    "id": "이수미_고유명사-1",
    "reason": "고유명사 (인명/지명)"
  },
  {
    "id": "이수지_고유명사-1",
    "reason": "고유명사 (인명/지명)"
  },
  {
    "id": "이영_고유명사-1",
    "reason": "고유명사 (인명/지명)"
  },
  {
    "id": "이재정_고유명사-1",
    "reason": "고유명사 (인명/지명)"
  },
  {
    "id": "이정진_고유명사-1",
    "reason": "고유명사 (인명/지명)"
  },
  {
    "id": "이준영_고유명사-1",
    "reason": "고유명사 (인명/지명)"
  },
  {
    "id": "이지영_고유명사-1",
    "reason": "고유명사 (인명/지명)"
  },
  {
    "id": "이집트_고유명사-1",
    "reason": "고유명사 (인명/지명)"
  },
  {
    "id": "이쪽_대명사-1",
    "reason": "기능적 요소 (대명사/의존명사)"
  },
  {
    "id": "이천시_고유명사-1",
    "reason": "고유명사 (인명/지명)"
  },
  {
    "id": "이태원_고유명사-1",
    "reason": "고유명사 (인명/지명)"
  },
  {
    "id": "이태원역_고유명사-1",
    "reason": "고유명사 (인명/지명)"
  },
  {
    "id": "이현_고유명사-1",
    "reason": "고유명사 (인명/지명)"
  },
  {
    "id": "이현석_고유명사-1",
    "reason": "고유명사 (인명/지명)"
  },
  {
    "id": "인도양_고유명사-1",
    "reason": "고유명사 (인명/지명)"
  },
  {
    "id": "인사동_고유명사-1",
    "reason": "고유명사 (인명/지명)"
  },
  {
    "id": "인천_고유명사-1",
    "reason": "고유명사 (인명/지명)"
  },
  {
    "id": "인천공항_고유명사-1",
    "reason": "고유명사 (인명/지명)"
  },
  {
    "id": "인천시_고유명사-1",
    "reason": "고유명사 (인명/지명)"
  },
  {
    "id": "인혜_고유명사-1",
    "reason": "고유명사 (인명/지명)"
  },
  {
    "id": "일본_고유명사-1",
    "reason": "고유명사 (인명/지명)"
  },
  {
    "id": "일본어_고유명사-1",
    "reason": "고유명사 (인명/지명)"
  },
  {
    "id": "일성록_고유명사-1",
    "reason": "고유명사 (인명/지명)"
  },
  {
    "id": "임원경제지_고유명사-1",
    "reason": "고유명사 (인명/지명)"
  },
  {
    "id": "자기_대명사-1",
    "reason": "기능적 요소 (대명사/의존명사)"
  },
  {
    "id": "자네_대명사-1",
    "reason": "기능적 요소 (대명사/의존명사)"
  },
  {
    "id": "작은소참진드기_고유명사-1",
    "reason": "고유명사 (인명/지명)"
  },
  {
    "id": "장기려_고유명사-1",
    "reason": "고유명사 (인명/지명)"
  },
  {
    "id": "장화_고유명사-1",
    "reason": "고유명사 (인명/지명)"
  },
  {
    "id": "장흥_고유명사-1",
    "reason": "고유명사 (인명/지명)"
  },
  {
    "id": "저_대명사-1",
    "reason": "기능적 요소 (대명사/의존명사)"
  },
  {
    "id": "저거_대명사-1",
    "reason": "기능적 요소 (대명사/의존명사)"
  },
  {
    "id": "저것_대명사-1",
    "reason": "기능적 요소 (대명사/의존명사)"
  },
  {
    "id": "저기_대명사-1",
    "reason": "기능적 요소 (대명사/의존명사)"
  },
  {
    "id": "저분_대명사-1",
    "reason": "기능적 요소 (대명사/의존명사)"
  },
  {
    "id": "저쪽_대명사-1",
    "reason": "기능적 요소 (대명사/의존명사)"
  },
  {
    "id": "저편_대명사-1",
    "reason": "기능적 요소 (대명사/의존명사)"
  },
  {
    "id": "저희_대명사-1",
    "reason": "기능적 요소 (대명사/의존명사)"
  },
  {
    "id": "적_의존명사-1",
    "reason": "기능적 요소 (대명사/의존명사)"
  },
  {
    "id": "적정기술_고유명사-1",
    "reason": "고유명사 (인명/지명)"
  },
  {
    "id": "전라도_고유명사-1",
    "reason": "고유명사 (인명/지명)"
  },
  {
    "id": "점_의존명사-1",
    "reason": "기능적 요소 (대명사/의존명사)"
  },
  {
    "id": "정남진_고유명사-1",
    "reason": "고유명사 (인명/지명)"
  },
  {
    "id": "정동진_고유명사-1",
    "reason": "고유명사 (인명/지명)"
  },
  {
    "id": "정지우_고유명사-1",
    "reason": "고유명사 (인명/지명)"
  },
  {
    "id": "제니_고유명사-1",
    "reason": "고유명사 (인명/지명)"
  },
  {
    "id": "제습기_고유명사-1",
    "reason": "고유명사 (인명/지명)"
  },
  {
    "id": "제인_고유명사-1",
    "reason": "고유명사 (인명/지명)"
  },
  {
    "id": "제임스_고유명사-1",
    "reason": "고유명사 (인명/지명)"
  },
  {
    "id": "제주_고유명사-1",
    "reason": "고유명사 (인명/지명)"
  },
  {
    "id": "제주도_고유명사-1",
    "reason": "고유명사 (인명/지명)"
  },
  {
    "id": "제주시_고유명사-1",
    "reason": "고유명사 (인명/지명)"
  },
  {
    "id": "조각보_고유명사-1",
    "reason": "고유명사 (인명/지명)"
  },
  {
    "id": "조선_고유명사-1",
    "reason": "고유명사 (인명/지명)"
  },
  {
    "id": "조선왕조실록_고유명사-1",
    "reason": "고유명사 (인명/지명)"
  },
  {
    "id": "종로_고유명사-1",
    "reason": "고유명사 (인명/지명)"
  },
  {
    "id": "종로구_고유명사-1",
    "reason": "고유명사 (인명/지명)"
  },
  {
    "id": "주년_의존명사-1",
    "reason": "기능적 요소 (대명사/의존명사)"
  },
  {
    "id": "주영_고유명사-1",
    "reason": "고유명사 (인명/지명)"
  },
  {
    "id": "죽비_고유명사-1",
    "reason": "고유명사 (인명/지명)"
  },
  {
    "id": "줄_의존명사-1",
    "reason": "기능적 요소 (대명사/의존명사)"
  },
  {
    "id": "중_의존명사-1",
    "reason": "기능적 요소 (대명사/의존명사)"
  },
  {
    "id": "중_의존명사-2",
    "reason": "기능적 요소 (대명사/의존명사)"
  },
  {
    "id": "중국_고유명사-1",
    "reason": "고유명사 (인명/지명)"
  },
  {
    "id": "중앙공원_고유명사-1",
    "reason": "고유명사 (인명/지명)"
  },
  {
    "id": "지경_의존명사-1",
    "reason": "기능적 요소 (대명사/의존명사)"
  },
  {
    "id": "지리산_고유명사-1",
    "reason": "고유명사 (인명/지명)"
  },
  {
    "id": "지영_고유명사-1",
    "reason": "고유명사 (인명/지명)"
  },
  {
    "id": "지은_고유명사-1",
    "reason": "고유명사 (인명/지명)"
  },
  {
    "id": "지중해_고유명사-1",
    "reason": "고유명사 (인명/지명)"
  },
  {
    "id": "지진학_고유명사-1",
    "reason": "고유명사 (인명/지명)"
  },
  {
    "id": "지현_고유명사-1",
    "reason": "고유명사 (인명/지명)"
  },
  {
    "id": "지훈_고유명사-1",
    "reason": "고유명사 (인명/지명)"
  },
  {
    "id": "진주조개_고유명사-1",
    "reason": "고유명사 (인명/지명)"
  },
  {
    "id": "쪽_의존명사-1",
    "reason": "기능적 요소 (대명사/의존명사)"
  },
  {
    "id": "쪽_의존명사-2",
    "reason": "기능적 요소 (대명사/의존명사)"
  },
  {
    "id": "찰리_고유명사-1",
    "reason": "고유명사 (인명/지명)"
  },
  {
    "id": "창경궁_고유명사-1",
    "reason": "고유명사 (인명/지명)"
  },
  {
    "id": "창덕궁_고유명사-1",
    "reason": "고유명사 (인명/지명)"
  },
  {
    "id": "채_의존명사-1",
    "reason": "기능적 요소 (대명사/의존명사)"
  },
  {
    "id": "채만식_고유명사-1",
    "reason": "고유명사 (인명/지명)"
  },
  {
    "id": "척_의존명사-1",
    "reason": "기능적 요소 (대명사/의존명사)"
  },
  {
    "id": "천칭자리_고유명사-1",
    "reason": "고유명사 (인명/지명)"
  },
  {
    "id": "철수_고유명사-1",
    "reason": "고유명사 (인명/지명)"
  },
  {
    "id": "청계천_고유명사-1",
    "reason": "고유명사 (인명/지명)"
  },
  {
    "id": "청양_고유명사-1",
    "reason": "고유명사 (인명/지명)"
  },
  {
    "id": "초_의존명사-1",
    "reason": "기능적 요소 (대명사/의존명사)"
  },
  {
    "id": "초코파이_고유명사-1",
    "reason": "고유명사 (인명/지명)"
  },
  {
    "id": "춘천_고유명사-1",
    "reason": "고유명사 (인명/지명)"
  },
  {
    "id": "측_의존명사-1",
    "reason": "기능적 요소 (대명사/의존명사)"
  },
  {
    "id": "치아바타_고유명사-1",
    "reason": "고유명사 (인명/지명)"
  },
  {
    "id": "카뉴_고유명사-1",
    "reason": "고유명사 (인명/지명)"
  },
  {
    "id": "카카오_고유명사-1",
    "reason": "고유명사 (인명/지명)"
  },
  {
    "id": "캐나다_고유명사-1",
    "reason": "고유명사 (인명/지명)"
  },
  {
    "id": "켤레_의존명사-1",
    "reason": "기능적 요소 (대명사/의존명사)"
  },
  {
    "id": "코알라_고유명사-1",
    "reason": "고유명사 (인명/지명)"
  },
  {
    "id": "코코_고유명사-1",
    "reason": "고유명사 (인명/지명)"
  },
  {
    "id": "콜라겐_고유명사-1",
    "reason": "고유명사 (인명/지명)"
  },
  {
    "id": "콜럼버스_고유명사-1",
    "reason": "고유명사 (인명/지명)"
  },
  {
    "id": "콩코드_고유명사-1",
    "reason": "고유명사 (인명/지명)"
  },
  {
    "id": "킬로_의존명사-1",
    "reason": "기능적 요소 (대명사/의존명사)"
  },
  {
    "id": "킬로미터_의존명사-1",
    "reason": "기능적 요소 (대명사/의존명사)"
  },
  {
    "id": "타넷_고유명사-1",
    "reason": "고유명사 (인명/지명)"
  },
  {
    "id": "타워_고유명사-1",
    "reason": "고유명사 (인명/지명)"
  },
  {
    "id": "타임스퀘어_고유명사-1",
    "reason": "고유명사 (인명/지명)"
  },
  {
    "id": "태국_고유명사-1",
    "reason": "고유명사 (인명/지명)"
  },
  {
    "id": "태국어_고유명사-1",
    "reason": "고유명사 (인명/지명)"
  },
  {
    "id": "태평양_고유명사-1",
    "reason": "고유명사 (인명/지명)"
  },
  {
    "id": "태평천하_고유명사-1",
    "reason": "고유명사 (인명/지명)"
  },
  {
    "id": "턱_의존명사-1",
    "reason": "기능적 요소 (대명사/의존명사)"
  },
  {
    "id": "판_의존명사-1",
    "reason": "기능적 요소 (대명사/의존명사)"
  },
  {
    "id": "편_의존명사-1",
    "reason": "기능적 요소 (대명사/의존명사)"
  },
  {
    "id": "편도체_고유명사-1",
    "reason": "고유명사 (인명/지명)"
  },
  {
    "id": "평_의존명사-1",
    "reason": "기능적 요소 (대명사/의존명사)"
  },
  {
    "id": "포일_고유명사-1",
    "reason": "고유명사 (인명/지명)"
  },
  {
    "id": "포항_고유명사-1",
    "reason": "고유명사 (인명/지명)"
  },
  {
    "id": "푸가스_고유명사-1",
    "reason": "고유명사 (인명/지명)"
  },
  {
    "id": "풍물놀이_고유명사-1",
    "reason": "고유명사 (인명/지명)"
  },
  {
    "id": "프란츠 카프카_고유명사-1",
    "reason": "고유명사 (인명/지명)"
  },
  {
    "id": "프랑스_고유명사-1",
    "reason": "고유명사 (인명/지명)"
  },
  {
    "id": "피렌체_고유명사-1",
    "reason": "고유명사 (인명/지명)"
  },
  {
    "id": "피카소_고유명사-1",
    "reason": "고유명사 (인명/지명)"
  },
  {
    "id": "하_고유명사-1",
    "reason": "고유명사 (인명/지명)"
  },
  {
    "id": "하고_접속조사-1",
    "reason": "기능적 요소 (대명사/의존명사)"
  },
  {
    "id": "하늘정원_고유명사-1",
    "reason": "고유명사 (인명/지명)"
  },
  {
    "id": "한강_고유명사-1",
    "reason": "고유명사 (인명/지명)"
  },
  {
    "id": "한강시민공원_고유명사-1",
    "reason": "고유명사 (인명/지명)"
  },
  {
    "id": "한국_고유명사-1",
    "reason": "고유명사 (인명/지명)"
  },
  {
    "id": "한국어_고유명사-1",
    "reason": "고유명사 (인명/지명)"
  },
  {
    "id": "한국전력공사_고유명사-1",
    "reason": "고유명사 (인명/지명)"
  },
  {
    "id": "한라산_고유명사-1",
    "reason": "고유명사 (인명/지명)"
  },
  {
    "id": "한민족_고유명사-1",
    "reason": "고유명사 (인명/지명)"
  },
  {
    "id": "한영수_고유명사-1",
    "reason": "고유명사 (인명/지명)"
  },
  {
    "id": "한옥마을_고유명사-1",
    "reason": "고유명사 (인명/지명)"
  },
  {
    "id": "해미_고유명사-1",
    "reason": "고유명사 (인명/지명)"
  },
  {
    "id": "해운대구_고유명사-1",
    "reason": "고유명사 (인명/지명)"
  },
  {
    "id": "현석_고유명사-1",
    "reason": "고유명사 (인명/지명)"
  },
  {
    "id": "현아_고유명사-1",
    "reason": "고유명사 (인명/지명)"
  },
  {
    "id": "호_의존명사-1",
    "reason": "기능적 요소 (대명사/의존명사)"
  },
  {
    "id": "호선_의존명사-1",
    "reason": "기능적 요소 (대명사/의존명사)"
  },
  {
    "id": "홍콩_고유명사-1",
    "reason": "고유명사 (인명/지명)"
  },
  {
    "id": "회_의존명사-1",
    "reason": "기능적 요소 (대명사/의존명사)"
  },
  {
    "id": "후드_고유명사-1",
    "reason": "고유명사 (인명/지명)"
  },
  {
    "id": "후크_고유명사-1",
    "reason": "고유명사 (인명/지명)"
  },
  {
    "id": "흥부_고유명사-1",
    "reason": "고유명사 (인명/지명)"
  },
  {
    "id": "흥부전_고유명사-1",
    "reason": "고유명사 (인명/지명)"
  },
  {
    "id": "힐링_고유명사-1",
    "reason": "고유명사 (인명/지명)"
  },
  {
    "id": "각_관형사-1",
    "reason": "여럿을 하나하나 가리키는 관형사로, 기능 요소에 해당합니다."
  },
  {
    "id": "결코_일반부사-1",
    "reason": "기능적 요소"
  },
  {
    "id": "계시다_동사-1",
    "reason": "'있다'의 높임말로 기능어에 해당"
  },
  {
    "id": "그라다_동사-1",
    "reason": "지시 대명사 '그'와 '하다'의 결합으로, 기능 요소에 해당합니다."
  },
  {
    "id": "그래_감탄사-1",
    "reason": "상대의 말에 동의하거나 확인할 때 쓰는 감탄사로, 기능 요소에 해당합니다."
  },
  {
    "id": "그래도_접속부사-1",
    "reason": "앞의 상황과 달리 기대한 대로 또는 여전히를 나타내는 접속부사로, 기능 요소에 해당합니다."
  },
  {
    "id": "그래서_접속부사-1",
    "reason": "앞의 내용이 뒤의 결과의 이유가 될 때 쓰는 접속부사로, 기능 요소에 해당합니다."
  },
  {
    "id": "그래야_접속부사-1",
    "reason": "앞의 방식대로 해야만 뒤의 일이 이루어진다는 뜻을 나타내는 접속부사로, 기능 요소에 해당합니다."
  },
  {
    "id": "그러게_감탄사-1",
    "reason": "상대의 말에 동의하거나 안타까움을 나타낼 때 쓰는 감탄사로, 기능 요소에 해당합니다."
  },
  {
    "id": "그러나_접속부사-1",
    "reason": "앞의 내용과 반대되거나 어긋나는 내용을 이을 때 쓰는 접속부사로, 기능 요소에 해당합니다."
  },
  {
    "id": "그러니_접속부사-1",
    "reason": "접속부사는 기능 요소로 분류되어 EXCLUDED 처리됩니다."
  },
  {
    "id": "그러니까_접속부사-1",
    "reason": "접속부사는 기능 요소로 분류되어 EXCLUDED 처리됩니다."
  },
  {
    "id": "그러다_동사-1",
    "reason": "지시 대명사 '그리하다'에서 파생된 동사로, 특정 의미보다는 앞선 내용을 지시하는 기능적 요소가 강하여 EXCLUDED 처리됩니다."
  },
  {
    "id": "그러다가_접속부사-1",
    "reason": "접속부사는 기능 요소로 분류되어 EXCLUDED 처리됩니다."
  },
  {
    "id": "그러면_접속부사-1",
    "reason": "접속부사는 기능 요소로 분류되어 EXCLUDED 처리됩니다."
  },
  {
    "id": "그러므로_접속부사-1",
    "reason": "접속부사는 기능 요소로 분류되어 EXCLUDED 처리됩니다."
  },
  {
    "id": "그러자_접속부사-1",
    "reason": "접속부사는 기능 요소로 분류되어 EXCLUDED 처리됩니다."
  },
  {
    "id": "그런_관형사-1",
    "reason": "관형사는 기능 요소로 분류되어 EXCLUDED 처리됩니다."
  },
  {
    "id": "그런데_접속부사-1",
    "reason": "접속부사는 기능 요소로 분류되어 EXCLUDED 처리됩니다."
  },
  {
    "id": "그럼_접속부사-1",
    "reason": "접속부사는 기능 요소로 분류되어 EXCLUDED 처리됩니다."
  },
  {
    "id": "그럼요_감탄사-1",
    "reason": "감탄사는 기능 요소로 분류되어 EXCLUDED 처리됩니다."
  },
  {
    "id": "그렇게_일반부사-1",
    "reason": "지시 대명사 '그리하다'에서 파생된 부사로, 특정 의미보다는 앞선 내용을 지시하는 기능적 요소가 강하여 EXCLUDED 처리됩니다."
  },
  {
    "id": "그렇다_형용사-1",
    "reason": "지시 대명사 '그리하다'에서 파생된 형용사로, 특정 의미보다는 앞선 내용을 지시하는 기능적 요소가 강하여 EXCLUDED 처리됩니다."
  },
  {
    "id": "그렇지만_접속부사-1",
    "reason": "접속부사는 기능 요소로 분류되어 EXCLUDED 처리됩니다."
  },
  {
    "id": "그리_일반부사-1",
    "reason": "지시 대명사 '그리하다'에서 파생된 부사로, 특정 의미보다는 앞선 내용을 지시하는 기능적 요소가 강하여 EXCLUDED 처리됩니다."
  },
  {
    "id": "그리고_접속부사-1",
    "reason": "접속부사는 기능 요소로 분류되어 EXCLUDED 처리됩니다."
  },
  {
    "id": "그리로_일반부사-1",
    "reason": "지시 대명사 '그리'에 조사 '로'가 붙은 형태로, 특정 의미보다는 앞선 내용을 지시하는 기능적 요소가 강하여 EXCLUDED 처리됩니다."
  },
  {
    "id": "그리하여_접속부사-1",
    "reason": "접속부사는 기능 요소로 분류되어 EXCLUDED 처리됩니다."
  },
  {
    "id": "그만큼_일반부사-1",
    "reason": "지시 대명사 '그'에 조사 '만큼'이 붙은 형태로, 특정 의미보다는 앞선 내용을 지시하는 기능적 요소가 강하여 EXCLUDED 처리됩니다."
  },
  {
    "id": "그토록_일반부사-1",
    "reason": "지시 대명사 '그'에 조사 '토록'이 붙은 형태로, 특정 의미보다는 앞선 내용을 지시하는 기능적 요소가 강하여 EXCLUDED 처리됩니다."
  },
  {
    "id": "근_관형사-1",
    "reason": "관형사는 기능 요소로 분류되어 EXCLUDED 처리됩니다."
  },
  {
    "id": "근데_접속부사-1",
    "reason": "접속부사는 기능 요소로 분류되어 EXCLUDED 처리됩니다."
  },
  {
    "id": "낚싯_일반명사-1",
    "reason": "특정 명사 앞에 붙어 의미를 한정하는 기능적 요소로, 어휘의 의미 자체를 나타내기보다 다른 어휘와의 관계를 설명하는 메타 언어적 성격이 강함."
  },
  {
    "id": "네_감탄사-1",
    "reason": "감탄사로 기능 요소에 해당"
  },
  {
    "id": "네안데르탈인_일반명사-1",
    "reason": "특정 인류 종족을 지칭하는 고유명사"
  },
  {
    "id": "다만_일반부사-1",
    "reason": "제한이나 예외를 나타내는 기능적인 부사입니다."
  },
  {
    "id": "단_접속부사-1",
    "reason": "앞말과 반대되거나 예외가 되는 내용을 이끌 때 쓰는 기능적인 접속 부사입니다."
  },
  {
    "id": "단지_일반부사-1",
    "reason": "다른 이유 없이 오직이라는 제한을 강조하는 기능적인 부사입니다."
  },
  {
    "id": "두_관형사-1",
    "reason": "수량을 나타내는 관형사로, 기능 요소에 해당합니다."
  },
  {
    "id": "따라서_접속부사-1",
    "reason": "접속부사로 기능 요소에 해당하여 제외."
  },
  {
    "id": "딴_관형사-1",
    "reason": "관형사로 기능 요소에 해당하여 제외."
  },
  {
    "id": "마치_일반부사-1",
    "reason": "기능 요소 (부사)"
  },
  {
    "id": "마침_일반부사-1",
    "reason": "기능 요소 (부사)"
  },
  {
    "id": "마침내_일반부사-1",
    "reason": "기능 요소 (부사)"
  },
  {
    "id": "마흔_수사-1",
    "reason": "기능 요소 (수사)"
  },
  {
    "id": "막상_일반부사-1",
    "reason": "기능 요소 (부사)"
  },
  {
    "id": "만약_일반명사-1",
    "reason": "기능 요소 (가정의 의미를 나타내는 명사)"
  },
  {
    "id": "만일_일반명사-1",
    "reason": "기능 요소 (가정의 의미를 나타내는 명사)"
  },
  {
    "id": "많이_일반부사-1",
    "reason": "기능 요소 (부사)"
  },
  {
    "id": "말없이_일반부사-1",
    "reason": "기능 요소 (부사)"
  },
  {
    "id": "몇_수사-1",
    "reason": "수량을 나타내는 기능어."
  },
  {
    "id": "몇몇_관형사-1",
    "reason": "수량을 한정하는 기능어."
  },
  {
    "id": "모든_관형사-1",
    "reason": "대상을 한정하는 기능어."
  },
  {
    "id": "무슨_관형사-1",
    "reason": "정체를 묻거나 강조하는 기능어."
  },
  {
    "id": "뭘_감탄사-1",
    "reason": "감탄사로, 기능 요소에 해당하여 제외함."
  },
  {
    "id": "및_일반부사-1",
    "reason": "접속 부사로, 문법적 기능을 하는 기능 요소이다."
  },
  {
    "id": "부산_고유명사-1",
    "reason": "고유명사로, 일반 어휘 분류 대상에서 제외된다."
  },
  {
    "id": "서울_고유명사-1",
    "reason": "고유명사이므로 EXCLUDED."
  },
  {
    "id": "스무_관형사-1",
    "reason": "수량을 나타내는 관형사로, 기능 요소에 해당합니다."
  },
  {
    "id": "스물세_관형사-1",
    "reason": "수량을 나타내는 관형사로, 기능 요소에 해당합니다."
  },
  {
    "id": "신라인_일반명사-1",
    "reason": "특정 시대에 살던 사람을 지칭하는 고유명사 파생어입니다."
  },
  {
    "id": "십_수사-1",
    "reason": "수사는 기능 요소로 분류되어 EXCLUDED 처리합니다."
  },
  {
    "id": "십만_수사-1",
    "reason": "수사는 기능 요소로 분류되어 EXCLUDED 처리합니다."
  },
  {
    "id": "십이_수사-1",
    "reason": "수사는 기능 요소로 분류되어 EXCLUDED 처리합니다."
  },
  {
    "id": "십일_수사-1",
    "reason": "수사는 기능 요소로 분류되어 EXCLUDED 처리합니다."
  },
  {
    "id": "아직_일반부사-1",
    "reason": "기능 요소 (부사)"
  },
  {
    "id": "아휴_감탄사-1",
    "reason": "기능 요소 (감탄사)"
  },
  {
    "id": "안_일반부사-1",
    "reason": "기능 요소 (부정 부사)"
  },
  {
    "id": "안녕_일반명사-2",
    "reason": "기능 요소 (인사말)"
  },
  {
    "id": "안녕히_일반부사-1",
    "reason": "기능 요소 (부사)"
  },
  {
    "id": "어_감탄사-1",
    "reason": "감탄사는 기능 요소로 분류된다."
  },
  {
    "id": "어느_관형사-1",
    "reason": "관형사는 기능 요소로 분류된다."
  },
  {
    "id": "어떤_관형사-1",
    "reason": "관형사는 기능 요소로 분류된다."
  },
  {
    "id": "어떻게_일반부사-1",
    "reason": "의문 부사로 기능 요소에 해당한다."
  },
  {
    "id": "어떻다_형용사-1",
    "reason": "의문 형용사로 기능 요소에 해당한다."
  },
  {
    "id": "어머_감탄사-1",
    "reason": "감탄사는 기능 요소로 분류된다."
  },
  {
    "id": "어쩌면_일반부사-1",
    "reason": "가능성을 나타내는 부사로 기능 요소에 해당한다."
  },
  {
    "id": "어찌나_일반부사-1",
    "reason": "정도를 강조하는 부사로 기능 요소에 해당한다."
  },
  {
    "id": "어휴_감탄사-1",
    "reason": "감탄사는 기능 요소로 분류된다."
  },
  {
    "id": "열다섯_수사-1",
    "reason": "수사는 기능 요소로 분류되어 제외됩니다."
  },
  {
    "id": "열두_수사-1",
    "reason": "수사는 기능 요소로 분류되어 제외됩니다."
  },
  {
    "id": "열일곱_수사-1",
    "reason": "수사는 기능 요소로 분류되어 제외됩니다."
  },
  {
    "id": "예컨대_일반부사-1",
    "reason": "'예를 들자면'이라는 의미로, 문장 내에서 특정 기능을 하는 부사이다."
  },
  {
    "id": "옛_관형사-1",
    "reason": "'아주 지난 때의'라는 의미로, 명사를 수식하는 관형사이다."
  },
  {
    "id": "오랜_관형사-1",
    "reason": "'시간이 꽤 많이 흐른'이라는 의미로, 명사를 수식하는 관형사이다."
  },
  {
    "id": "오로지_일반부사-1",
    "reason": "'한가지만'이라는 의미로, 다른 것을 배제하고 특정 대상을 강조하는 부사이다."
  },
  {
    "id": "오직_일반부사-1",
    "reason": "'한가지만'이라는 의미로, 다른 것을 배제하고 특정 대상을 강조하는 부사이다."
  },
  {
    "id": "이_관형사-1",
    "reason": "지시 관형사로, 기능 요소에 해당하여 제외합니다."
  },
  {
    "id": "이것저것_일반명사-1",
    "reason": "여러 가지 서로 다른 것을 지칭하는 대명사적 표현으로, 기능 요소에 해당하여 제외합니다."
  },
  {
    "id": "이날_일반명사-1",
    "reason": "특정 날짜를 지칭하는 대명사적 표현으로, 기능 요소에 해당하여 제외합니다."
  },
  {
    "id": "이다_긍정지정사-1",
    "reason": "긍정지정사로, 기능 요소에 해당하여 제외합니다."
  },
  {
    "id": "이때_일반명사-1",
    "reason": "특정 시점을 지칭하는 대명사적 표현으로, 기능 요소에 해당하여 제외합니다."
  },
  {
    "id": "이러하다_형용사-1",
    "reason": "앞에서 말한 것과 같은 모양이나 상태를 지시하는 형용사로, 기능 요소에 해당하여 제외합니다."
  },
  {
    "id": "이런_관형사-1",
    "reason": "지시 관형사로, 기능 요소에 해당하여 제외합니다."
  },
  {
    "id": "이런저런_관형사-1",
    "reason": "여러 가지 서로 다른 것을 지시하는 관형사로, 기능 요소에 해당하여 제외합니다."
  },
  {
    "id": "이렇게_일반부사-1",
    "reason": "지금과 같은 방식이나 정도로를 지시하는 부사로, 기능 요소에 해당하여 제외합니다."
  },
  {
    "id": "이렇다_형용사-1",
    "reason": "지금과 같은 상태를 지시하는 형용사로, 기능 요소에 해당하여 제외합니다."
  },
  {
    "id": "이봐요_감탄사-1",
    "reason": "감탄사로, 기능어에 해당하여 제외합니다."
  },
  {
    "id": "일곱_수사-1",
    "reason": "수사는 기능 요소로 분류됩니다."
  },
  {
    "id": "일단_일반부사-1",
    "reason": "부사는 기능 요소로 분류됩니다."
  },
  {
    "id": "일부러_일반부사-1",
    "reason": "부사는 기능 요소로 분류됩니다."
  },
  {
    "id": "자신_일반명사-1",
    "reason": "자기 스스로를 지칭하는 대명사적 기능 요소임."
  },
  {
    "id": "자체_일반명사-1",
    "reason": "다른 것이 아닌 바로 그것 스스로를 지칭하는 기능 요소임."
  },
  {
    "id": "제_관형사-1",
    "reason": "관형사는 기능 요소에 해당합니다."
  },
  {
    "id": "조사_일반명사-2",
    "reason": "체언 뒤에 붙어 문법적 관계를 나타내는 기능 요소임."
  },
  {
    "id": "주술_일반명사-2",
    "reason": "문법 용어로, 메타 언어 트랩에 해당하여 제외."
  },
  {
    "id": "주제_일반명사-1",
    "reason": "글이나 이야기의 중심 내용을 의미하는 메타 언어 용어로, 제외."
  },
  {
    "id": "주제문_일반명사-1",
    "reason": "문단의 중심 생각을 나타내는 문법 용어로, 메타 언어 트랩에 해당하여 제외."
  },
  {
    "id": "타_관형사-1",
    "reason": "자신이 아닌 다른 것을 지칭하는 관형사로, 기능 요소에 해당한다."
  },
  {
    "id": "하기야_접속부사-1",
    "reason": "접속 부사로, 문장 간의 관계를 이어주는 기능어에 해당함."
  },
  {
    "id": "하긴_접속부사-1",
    "reason": "접속 부사로, 문장 간의 관계를 이어주는 기능어에 해당함."
  },
  {
    "id": "하여간_일반부사-1",
    "reason": "접속 부사로, 문장 간의 관계를 이어주는 기능어에 해당함."
  },
  {
    "id": "하지만_접속부사-1",
    "reason": "접속 부사로, 문장 간의 관계를 이어주는 기능어에 해당함."
  },
  {
    "id": "한_관형사-1",
    "reason": "수나 양이 하나뿐임을 나타내는 관형사로 기능 요소에 해당합니다."
  },
  {
    "id": "한결_일반부사-1",
    "reason": "전보다 더 한층의 의미를 가지는 부사로 기능 요소에 해당합니다."
  },
  {
    "id": "한꺼번에_일반부사-1",
    "reason": "여러 일을 동시에 또는 한 번에의 의미를 가지는 부사로 기능 요소에 해당합니다."
  },
  {
    "id": "한껏_일반부사-1",
    "reason": "가능한 만큼 가장 크게의 의미를 가지는 부사로 기능 요소에 해당합니다."
  },
  {
    "id": "한두_관형사-1",
    "reason": "수량이 하나 또는 둘 정도임을 나타내는 관형사로 기능 요소에 해당합니다."
  },
  {
    "id": "한둘_수사-1",
    "reason": "하나나 둘쯤 되는 적은 수를 나타내는 수사로 기능 요소에 해당합니다."
  },
  {
    "id": "한번_일반부사-1",
    "reason": "어떤 일을 한 차례의 의미를 가지는 부사로 기능 요소에 해당합니다."
  },
  {
    "id": "한참_일반부사-1",
    "reason": "꽤 오랫동안의 의미를 가지는 부사로 기능 요소에 해당합니다."
  },
  {
    "id": "한층_일반부사-1",
    "reason": "전보다 더 높게 또는 더 많이의 의미를 가지는 부사로 기능 요소에 해당합니다."
  },
  {
    "id": "한편_접속부사-1",
    "reason": "앞의 내용과 다른 면이나 다른 이야기를 이을 때 쓰는 말은 접속 부사로 기능 요소에 해당합니다."
  },
  {
    "id": "함께_일반부사-1",
    "reason": "여럿이 서로 어울려 같이의 의미를 가지는 부사로 기능 요소에 해당합니다."
  },
  {
    "id": "함부로_일반부사-1",
    "reason": "조심하지 않고 아무렇게나의 의미를 가지는 부사로 기능 요소에 해당합니다."
  },
  {
    "id": "개_의존명사-1",
    "reason": "기능적 요소 (대명사/의존명사)"
  },
  {
    "id": "교시_의존명사-1",
    "reason": "기능적 요소 (대명사/의존명사)"
  },
  {
    "id": "권_의존명사-1",
    "reason": "기능적 요소 (대명사/의존명사)"
  },
  {
    "id": "그램_의존명사-1",
    "reason": "기능적 요소 (대명사/의존명사)"
  },
  {
    "id": "그쪽_대명사-1",
    "reason": "기능적 요소 (대명사/의존명사)"
  },
  {
    "id": "나_대명사-1",
    "reason": "기능적 요소 (대명사/의존명사)"
  },
  {
    "id": "내_대명사-1",
    "reason": "기능적 요소 (대명사/의존명사)"
  },
  {
    "id": "너_대명사-1",
    "reason": "기능적 요소 (대명사/의존명사)"
  },
  {
    "id": "너희_대명사-1",
    "reason": "기능적 요소 (대명사/의존명사)"
  },
  {
    "id": "네_대명사-1",
    "reason": "기능적 요소 (대명사/의존명사)"
  },
  {
    "id": "녀석_의존명사-1",
    "reason": "기능적 요소 (대명사/의존명사)"
  },
  {
    "id": "님_의존명사-1",
    "reason": "기능적 요소 (대명사/의존명사)"
  },
  {
    "id": "도_의존명사-1",
    "reason": "기능적 요소 (대명사/의존명사)"
  },
  {
    "id": "리터_의존명사-1",
    "reason": "기능적 요소 (대명사/의존명사)"
  },
  {
    "id": "말_의존명사-1",
    "reason": "기능적 요소 (대명사/의존명사)"
  },
  {
    "id": "박_의존명사-1",
    "reason": "기능적 요소 (대명사/의존명사)"
  },
  {
    "id": "번째_의존명사-1",
    "reason": "기능적 요소 (대명사/의존명사)"
  },
  {
    "id": "벌_의존명사-1",
    "reason": "기능적 요소 (대명사/의존명사)"
  },
  {
    "id": "살_의존명사-1",
    "reason": "기능적 요소 (대명사/의존명사)"
  },
  {
    "id": "세_의존명사-1",
    "reason": "기능적 요소 (대명사/의존명사)"
  },
  {
    "id": "시_의존명사-1",
    "reason": "기능적 요소 (대명사/의존명사)"
  },
  {
    "id": "아무_대명사-1",
    "reason": "기능적 요소 (대명사/의존명사)"
  },
  {
    "id": "얘_대명사-1",
    "reason": "기능적 요소 (대명사/의존명사)"
  },
  {
    "id": "위_의존명사-1",
    "reason": "기능적 요소 (대명사/의존명사)"
  },
  {
    "id": "이_대명사-1",
    "reason": "기능적 요소 (대명사/의존명사)"
  },
  {
    "id": "이분_대명사-1",
    "reason": "기능적 요소 (대명사/의존명사)"
  },
  {
    "id": "인분_의존명사-1",
    "reason": "기능적 요소 (대명사/의존명사)"
  },
  {
    "id": "일_의존명사-1",
    "reason": "기능적 요소 (대명사/의존명사)"
  },
  {
    "id": "장_의존명사-1",
    "reason": "기능적 요소 (대명사/의존명사)"
  },
  {
    "id": "저곳_대명사-1",
    "reason": "기능적 요소 (대명사/의존명사)"
  },
  {
    "id": "제_대명사-1",
    "reason": "기능적 요소 (대명사/의존명사)"
  },
  {
    "id": "주_의존명사-1",
    "reason": "기능적 요소 (대명사/의존명사)"
  },
  {
    "id": "퍼센트_의존명사-1",
    "reason": "기능적 요소 (대명사/의존명사)"
  },
  {
    "id": "걔_일반명사-1",
    "reason": "'그 아이'의 줄임말로, 대명사에 해당"
  },
  {
    "id": "구_수사-1",
    "reason": "수사는 기능 요소에 해당"
  },
  {
    "id": "구십_수사-1",
    "reason": "수사는 기능 요소에 해당"
  },
  {
    "id": "귀하_일반명사-1",
    "reason": "편지나 물건을 받을 사람의 이름 뒤에 붙여 쓰는 높임말은 기능 요소에 해당"
  },
  {
    "id": "그나마_일반부사-1",
    "reason": "일반부사는 기능 요소에 해당"
  },
  {
    "id": "그_관형사-1",
    "reason": "관형사는 기능 요소에 해당"
  },
  {
    "id": "그래서_일반부사-1",
    "reason": "일반부사는 기능 요소에 해당"
  },
  {
    "id": "그러나_일반부사-1",
    "reason": "일반부사는 기능 요소에 해당"
  },
  {
    "id": "그러므로_일반부사-1",
    "reason": "일반부사는 기능 요소에 해당"
  },
  {
    "id": "그러니까_일반부사-1",
    "reason": "일반부사는 기능 요소에 해당"
  },
  {
    "id": "그러면_일반부사-1",
    "reason": "일반부사는 기능 요소에 해당"
  },
  {
    "id": "그런데_일반부사-1",
    "reason": "일반부사는 기능 요소에 해당"
  },
  {
    "id": "그렇지_감탄사-1",
    "reason": "감탄사는 기능 요소에 해당"
  },
  {
    "id": "그럼_일반부사-1",
    "reason": "일반부사는 기능 요소에 해당"
  },
  {
    "id": "그렇지만_일반부사-1",
    "reason": "일반부사는 기능 요소에 해당"
  },
  {
    "id": "그럼_감탄사-1",
    "reason": "감탄사는 기능 요소에 해당"
  },
  {
    "id": "그리고_일반부사-1",
    "reason": "일반부사는 기능 요소에 해당"
  },
  {
    "id": "네_관형사-1",
    "reason": "관형사는 기능어로 분류"
  },
  {
    "id": "넷째_수사-1",
    "reason": "수사는 기능어로 분류"
  },
  {
    "id": "다섯째_수사-1",
    "reason": "수사는 기능어로 분류"
  },
  {
    "id": "단_관형사-1",
    "reason": "관형사는 기능어로 분류"
  },
  {
    "id": "대한민국_일반명사-1",
    "reason": "특정 국가를 지칭하는 고유명사."
  },
  {
    "id": "독일_일반명사-1",
    "reason": "특정 국가를 지칭하는 고유명사."
  },
  {
    "id": "독일어_일반명사-1",
    "reason": "특정 언어를 지칭하는 고유명사."
  },
  {
    "id": "미국_일반명사-1",
    "reason": "고유명사 (특정 국가명)"
  },
  {
    "id": "불구하고_동사-1",
    "reason": "문장 간의 논리적 관계를 연결하는 기능적 요소."
  },
  {
    "id": "서울_일반명사-1",
    "reason": "고유명사 (특정 도시 이름)."
  },
  {
    "id": "아시아_일반명사-1",
    "reason": "고유명사로 EXCLUDED 처리."
  },
  {
    "id": "아이고_감탄사-1",
    "reason": "감탄사로 EXCLUDED 처리."
  },
  {
    "id": "아프리카_일반명사-1",
    "reason": "특정 대륙을 지칭하는 고유명사입니다."
  },
  {
    "id": "아하_감탄사-1",
    "reason": "깨달음을 표현하는 감탄사로, 기능 요소에 해당합니다."
  },
  {
    "id": "안녕_감탄사-1",
    "reason": "인사말에 사용되는 감탄사로, 기능 요소에 해당합니다."
  },
  {
    "id": "앗_감탄사-1",
    "reason": "놀랐을 때 내는 감탄사로, 기능 요소에 해당합니다."
  },
  {
    "id": "야_감탄사-1",
    "reason": "놀라거나 반가울 때 내는 감탄사로, 기능 요소에 해당합니다."
  },
  {
    "id": "여덟째_수사-1",
    "reason": "수사는 기능 요소로 분류되어 EXCLUDED 처리됩니다."
  },
  {
    "id": "여섯째_수사-1",
    "reason": "수사는 기능 요소로 분류되어 EXCLUDED 처리됩니다."
  },
  {
    "id": "열_수사-1",
    "reason": "수사는 기능 요소로 분류되어 EXCLUDED 처리됩니다."
  },
  {
    "id": "열째_수사-1",
    "reason": "수사는 기능 요소로 분류되어 EXCLUDED 처리됩니다."
  },
  {
    "id": "영_일반부사-1",
    "reason": "부사는 기능 요소로 분류되어 EXCLUDED 처리됩니다."
  },
  {
    "id": "영국_일반명사-1",
    "reason": "특정 국가의 고유명사이므로 EXCLUDED 처리됩니다."
  },
  {
    "id": "영어_일반명사-1",
    "reason": "특정 언어의 고유명사이므로 EXCLUDED 처리됩니다."
  },
  {
    "id": "예_감탄사-1",
    "reason": "감탄사는 기능 요소로 분류되어 EXCLUDED 처리됩니다."
  },
  {
    "id": "예순_수사-1",
    "reason": "수사는 기능 요소로 분류되어 EXCLUDED 처리됩니다."
  },
  {
    "id": "오_감탄사-1",
    "reason": "감탄사는 기능 요소로 분류되어 EXCLUDED 처리됩니다."
  },
  {
    "id": "오_수사-1",
    "reason": "수사는 기능 요소로 분류되어 EXCLUDED 처리됩니다."
  },
  {
    "id": "오십_수사-1",
    "reason": "수사는 기능 요소로 분류되어 EXCLUDED 처리됩니다."
  },
  {
    "id": "와_감탄사-1",
    "reason": "감탄사는 기능 요소로 분류되어 EXCLUDED 처리됩니다."
  },
  {
    "id": "왠지_일반부사-1",
    "reason": "부사는 기능 요소로 분류되어 EXCLUDED 처리됩니다."
  },
  {
    "id": "요_관형사-1",
    "reason": "지시 기능을 하는 관형사로, 기능 요소에 해당합니다."
  },
  {
    "id": "웬_관형사-1",
    "reason": "의문 또는 막연한 지시 기능을 하는 관형사로, 기능 요소에 해당합니다."
  },
  {
    "id": "음_감탄사-1",
    "reason": "감정을 표현하는 감탄사로, 기능 요소에 해당합니다."
  },
  {
    "id": "으악_감탄사-1",
    "reason": "감정을 표현하는 감탄사로, 기능 요소에 해당합니다."
  },
  {
    "id": "자_감탄사-1",
    "reason": "감탄사로 기능어에 해당합니다."
  },
  {
    "id": "자기_일반명사-1",
    "reason": "대명사적 성격이 강한 기능어입니다."
  },
  {
    "id": "쟤_일반명사-1",
    "reason": "'저 아이'의 준말로, 대명사적 기능을 합니다."
  },
  {
    "id": "저_관형사-1",
    "reason": "대상을 가리키는 지시 관형사입니다."
  },
  {
    "id": "저_감탄사-1",
    "reason": "말이 잘 생각나지 않을 때 쓰는 감탄사입니다."
  },
  {
    "id": "저기_감탄사-1",
    "reason": "생각이 잘 나지 않을 때 쓰는 감탄사입니다."
  },
  {
    "id": "제주도_일반명사-1",
    "reason": "한국의 특정 행정 구역을 지칭하는 고유명사입니다."
  },
  {
    "id": "중국_일반명사-1",
    "reason": "고유명사 (국가명)."
  },
  {
    "id": "태국_일반명사-1",
    "reason": "고유명사 (국가명)"
  },
  {
    "id": "텅_일반부사-1",
    "reason": "일반 부사"
  },
  {
    "id": "통_일반부사-1",
    "reason": "일반 부사"
  },
  {
    "id": "틀림없이_일반부사-1",
    "reason": "일반 부사"
  },
  {
    "id": "팔_수사-1",
    "reason": "수사"
  },
  {
    "id": "팔십_수사-1",
    "reason": "수사"
  },
  {
    "id": "퍽_일반부사-1",
    "reason": "일반 부사"
  },
  {
    "id": "하긴_일반부사-1",
    "reason": "일반 부사"
  },
  {
    "id": "하여튼_일반부사-1",
    "reason": "일반 부사"
  },
  {
    "id": "하지만_일반부사-1",
    "reason": "일반 부사 (접속 부사)"
  },
  {
    "id": "하하_일반부사-1",
    "reason": "의성/의태 부사"
  },
  {
    "id": "한국_일반명사-1",
    "reason": "고유명사 (국가명)"
  },
  {
    "id": "한때_일반부사-1",
    "reason": "일반 부사"
  }
]